aiClient/AiBaseClient.py
aiClient/ContextAwarenessClient.py
aiClient/DataManagementClient.py
aiClient/KnowledgeGraphClient.py
aiClient/NaturalLanguageProcessingClient.py
aiClient/VisionTechnologiesClient.py
aiClient/VoiceTechnologiesClient.py
aiClient/__init__.py
aiClient/utils/ApiUrl.py
aiClient/utils/CaRequestProcess.py
aiClient/utils/KgRequestProcess.py
aiClient/utils/NLPRequestProcess.py
aiClient/utils/VisionRequestProcess.py
aiClient/utils/VoiceRequestProcess.py
aiClient/utils/__init__.py
sampleCode/__init__.py
sampleCode/context_awareness.py
sampleCode/data_management.py
sampleCode/knowledge_graph.py
sampleCode/natural_language_processing_client.py
sampleCode/vision_technologies.py
sampleCode/voice_technologies_client.py
Lenovo_Ai_Client-0.0.1.dist-info/LICENSE
Lenovo_Ai_Client-0.0.1.dist-info/METADATA
Lenovo_Ai_Client-0.0.1.dist-info/WHEEL
Lenovo_Ai_Client-0.0.1.dist-info/top_level.txt
Lenovo_Ai_Client-0.0.1.dist-info/RECORD
