Metadata-Version: 2.1
Name: Lenovo-Ai-Client
Version: 0.0.1
Summary: A Lenovo SDK package
Home-page: https://github.com/chenjie222/ai_client
Author: Chen jie
Author-email: chenjie_222@163.com
License: Apache License
Platform: UNKNOWN
Classifier: Programming Language :: Python :: 3
Classifier: License :: OSI Approved :: MIT License
Classifier: Operating System :: OS Independent
Requires-Dist: requests
Requires-Dist: simplejson
Requires-Dist: opencv-python
Requires-Dist: jsonpath
